Metadata-Version: 2.1
Name: adafruit-circuitpython-pixelbuf
Version: 2.0.2
Summary: A pure Python implementation of adafruit_pixelbuf for smaller boards.
Author-email: Adafruit Industries <circuitpython@adafruit.com>
License: MIT
Project-URL: Homepage, https://github.com/adafruit/Adafruit_CircuitPython_Pixelbuf.git
Keywords: adafruit,blinka,circuitpython,micropython,pixelbuf,neopixel,dotstar,leds
Classifier: Intended Audience :: Developers
Classifier: Topic :: Software Development :: Libraries
Classifier: Topic :: Software Development :: Embedded Systems
Classifier: Topic :: System :: Hardware
Classifier: License :: OSI Approved :: MIT License
Classifier: Programming Language :: Python :: 3
License-File: LICENSE
Requires-Dist: Adafruit-Blinka
Provides-Extra: optional
